toyota_na/__init__.py
toyota_na/app.py
toyota_na/auth.py
toyota_na/client.py
toyota_na/exceptions.py
toyota_na/vehicle/__init__.py
toyota_na/vehicle/base_vehicle.py
toyota_na/vehicle/vehicle.py
toyota_na/vehicle/entity_types/ToyotaLocation.py
toyota_na/vehicle/entity_types/ToyotaLockableOpening.py
toyota_na/vehicle/entity_types/ToyotaNumeric.py
toyota_na/vehicle/entity_types/ToyotaOpening.py
toyota_na/vehicle/entity_types/ToyotaRemoteStart.py
toyota_na/vehicle/entity_types/__init__.py
toyota_na/vehicle/vehicle_generations/__init__.py
toyota_na/vehicle/vehicle_generations/seventeen_cy.py
toyota_na/vehicle/vehicle_generations/seventeen_cy_plus.py
lexus_na-2.1.1.11.dist-info/LICENSE
lexus_na-2.1.1.11.dist-info/METADATA
lexus_na-2.1.1.11.dist-info/WHEEL
lexus_na-2.1.1.11.dist-info/top_level.txt
lexus_na-2.1.1.11.dist-info/RECORD
